browser_driver_manager/__init__.py
browser_driver_manager/browser_driver_manager.py
browser_driver_manager-1.0.4.dist-info/METADATA
browser_driver_manager-1.0.4.dist-info/WHEEL
browser_driver_manager-1.0.4.dist-info/top_level.txt
browser_driver_manager-1.0.4.dist-info/RECORD
