Metadata-Version: 2.1
Name: browser-driver-manager
Version: 1.0.4
Summary: 用于管理浏览器驱动程序的下载和安装
Home-page: https://github.com/weqq2019/browser_driver_manager
Author: 刘泉
Author-email: soundless2023@gmail.com
Classifier: Development Status :: 5 - Production/Stable
Classifier: Intended Audience :: Developers
Classifier: License :: OSI Approved :: MIT License
Classifier: Programming Language :: Python :: 3
Classifier: Programming Language :: Python :: 3.6
Classifier: Programming Language :: Python :: 3.7
Classifier: Programming Language :: Python :: 3.8
Classifier: Programming Language :: Python :: 3.9
Classifier: Programming Language :: Python :: 3.10
Classifier: Programming Language :: Python :: 3.11
Requires-Dist: requests
